{ "X3D": {
    "encoding":"UTF-8",
    "@profile":"Full",
    "@version":"3.3",
    "@xsd:noNamespaceSchemaLocation":"http://www.web3d.org/specifications/x3d-3.3.xsd",
    "JSON schema":"https://www.web3d.org/specifications/x3d-3.3-JSONSchema.json",
    "head": {
        "meta": [
          {
            "@name":"comment",
            "@content":"World of Titania"
          },
          {
            "@name":"created",
            "@content":"Thu, 23 Apr 2015 06:06:59 GMT"
          },
          {
            "@name":"creator",
            "@content":"Holger Seelig"
          },
          {
            "@name":"generator",
            "@content":"Titania V0.7.8, http://titania.create3000.de"
          },
          {
            "@name":"modified",
            "@content":"Thu, 23 Apr 2015 06:06:59 GMT"
          },
          {
            "@name":"translated",
            "@content":"17 January 2022"
          },
          {
            "@name":"generator",
            "@content":"X3dToJson.xslt, https://www.web3d.org/x3d/stylesheets/X3dToJson.html"
          },
          {
            "@name":"reference",
            "@content":"X3D JSON encoding: https://www.web3d.org/wiki/index.php/X3D_JSON_Encoding"
          }
        ]
    },
    "Scene": {
        "-children":[
          { "WorldInfo":
            {
              "@info":[", ","Created in TitaniaPackaged by CosmoPackage"]
            }
          },
          { "Anchor":
            {
              "@url":["javascript: function tmt_winLaunch(theURL,winName,targetName,features) { eval(winName+\"=window.open('\"+theURL+\"','\"+targetName+\"','\"+features+\"')\") } tmt_winLaunch('html/cinema/clockwork.html', 'cinemaxx','cinemaxx','width=623,height=454,left=0,top=0');"],
              "-children":[
                { "Collision":
                  {
                    "@enabled":false,
                    "-children":[
                      { "Transform":
                        {
                          "-children":[
                            { "Transform":
                              {
                                "@DEF":"filmplakat",
                                "@scale":[4.95,4.94926,4.94979],
                                "-children":[
                                  { "Shape":
                                    {
                                      "-appearance":
                                        { "Appearance":
                                          {
                                            "-texture":
                                              { "ImageTexture":
                                                {
                                                  "@url":["clockwork.jpg"]
                                                }
                                              }
                                          }
                                        },
                                      "-geometry":
                                        { "IndexedFaceSet":
                                          {
                                            "@solid":false,
                                            "@coordIndex":[0,1,2,3,-1,4,5,6,7,-1],
                                            "-texCoord":
                                              { "TextureCoordinate":
                                                {
                                                  "@point":[0,0,1,0,1,1,0,1,0,0,1,0,1,1,0,1]
                                                }
                                              },
                                            "-coord":
                                              { "Coordinate":
                                                {
                                                  "@point":[-0.5,0.337629,0,0.5,0.337629,0,0.5,1.88983,0,-0.5,1.88983,0,-0.5,-0.362414,0,0.5,-0.362414,0,0.5,-1.88649,0,-0.5,-1.88649,0]
                                                }
                                              }
                                          }
                                        }
                                    }
                                  }
                                ]
                              }
                            }
                          ]
                        }
                      },
                      { "LOD":
                        {
                          "@range":[12],
                          "-children":[
                            { "Transform":
                              {
                                "@translation":[0,-0.970178,0],
                                "-children":[
                                  { "Transform":
                                    {
                                      "@DEF":"b",
                                      "@translation":[-0.036226,2.95521,-0.941064],
                                      "@rotation":[1,0,0,1.5708],
                                      "@scale":[6.56332,0.999999,1.20494],
                                      "-children":[
                                        { "Shape":
                                          {
                                            "-appearance":
                                              { "Appearance":
                                                {
                                                  "-material":
                                                    { "Material":
                                                      {
                                                        "@ambientIntensity":0,
                                                        "@diffuseColor":[0,0,0],
                                                        "@emissiveColor":[0.43617,0,0.0460901],
                                                        "@shininess":0,
                                                        "@transparency":0.265957
                                                      }
                                                    }
                                                }
                                              },
                                            "-geometry":
                                              { "IndexedFaceSet":
                                                {
                                                  "@creaseAngle":0.5,
                                                  "@coordIndex":[0,1,2,3,-1],
                                                  "-coord":
                                                    { "Coordinate":
                                                      {
                                                        "@point":[-1,1,-1,-1,1,1,1,1,1,1,1,-1]
                                                      }
                                                    }
                                                }
                                              }
                                          }
                                        }
                                      ]
                                    }
                                  },
                                  { "Transform":
                                    {
                                      "@DEF":"t",
                                      "@translation":[-0.0362264,3.40265,0.199348],
                                      "@scale":[0.0304876,0.0304875,0.0304875],
                                      "-children":[
                                        { "Shape":
                                          {
                                            "-appearance":
                                              { "Appearance":
                                                {
                                                  "-material":
                                                    { "Material":
                                                      {
                                                        "@ambientIntensity":0,
                                                        "@diffuseColor":[0,0,0],
                                                        "@emissiveColor":[1,0.842126,0],
                                                        "@shininess":0
                                                      }
                                                    }
                                                }
                                              },
                                            "-geometry":
                                              { "Text":
                                                {
                                                  "@string":["\"CLOCKWORK ORANGE\""],
                                                  "@length":[0],
                                                  "-fontStyle":
                                                    { "FontStyle":
                                                      {
                                                        "@family":["SANS"],
                                                        "@style":"BOLD",
                                                        "@size":24,
                                                        "@justify":["MIDDLE"]
                                                      }
                                                    }
                                                }
                                              }
                                          }
                                        }
                                      ]
                                    }
                                  },
                                  { "Transform":
                                    {
                                      "@DEF":"f",
                                      "@translation":[-6.29659,2.92385,0.195083],
                                      "@scale":[0.0285384,0.0285384,0.0285383],
                                      "-children":[
                                        { "Shape":
                                          {
                                            "-appearance":
                                              { "Appearance":
                                                {
                                                  "-material":
                                                    { "Material":
                                                      {
                                                        "@ambientIntensity":0,
                                                        "@diffuseColor":[0,0,0],
                                                        "@emissiveColor":[1,1,1],
                                                        "@shininess":0
                                                      }
                                                    }
                                                }
                                              },
                                            "-geometry":
                                              { "Text":
                                                {
                                                  "@string":["Die gefühlvolle Verfilmung des Frank-Sinatra-Hits \", ","I'm Singing In TheRain\" , ","- Tanzen mit Fremden leichtgemacht...Kinostart: Herbst"],
                                                  "@length":[0],
                                                  "-fontStyle":
                                                    { "FontStyle":
                                                      {
                                                        "@family":["SANS"],
                                                        "@size":14
                                                      }
                                                    }
                                                }
                                              }
                                          }
                                        }
                                      ]
                                    }
                                  }
                                ]
                              }
                            },
                            { "Transform":
                              {
                              }
                            }
                          ]
                        }
                      }
                    ]
                  }
                }
              ]
            }
          }
        ]
    }
  }
}