{ "X3D": {
    "encoding":"UTF-8",
    "@profile":"Full",
    "@version":"3.3",
    "@xsd:noNamespaceSchemaLocation":"http://www.web3d.org/specifications/x3d-3.3.xsd",
    "JSON schema":"https://www.web3d.org/specifications/x3d-3.3-JSONSchema.json",
    "head": {
        "meta": [
          {
            "@name":"comment",
            "@content":"World of Titania"
          },
          {
            "@name":"created",
            "@content":"Sat, 25 Apr 2015 12:38:25 GMT"
          },
          {
            "@name":"creator",
            "@content":"Holger Seelig"
          },
          {
            "@name":"generator",
            "@content":"Titania V0.7.8, http://titania.create3000.de"
          },
          {
            "@name":"modified",
            "@content":"Sat, 25 Apr 2015 12:38:25 GMT"
          },
          {
            "@name":"translated",
            "@content":"17 January 2022"
          },
          {
            "@name":"generator",
            "@content":"X3dToJson.xslt, https://www.web3d.org/x3d/stylesheets/X3dToJson.html"
          },
          {
            "@name":"reference",
            "@content":"X3D JSON encoding: https://www.web3d.org/wiki/index.php/X3D_JSON_Encoding"
          }
        ]
    },
    "Scene": {
        "-children":[
          { "ExternProtoDeclare":
            {
              "@name":"World",
              "@url":["World_proto.x3d"],
              "field": [
                {
                  "@name":"enabled",
                  "@accessType":"inputOutput",
                  "@type":"SFBool"
                },
                {
                  "@name":"startTime",
                  "@accessType":"inputOutput",
                  "@type":"SFTime"
                },
                {
                  "@name":"stopTime",
                  "@accessType":"inputOutput",
                  "@type":"SFTime"
                },
                {
                  "@name":"isActive",
                  "@accessType":"outputOnly",
                  "@type":"SFBool"
                },
                {
                  "@name":"enterTime",
                  "@accessType":"outputOnly",
                  "@type":"SFTime"
                },
                {
                  "@name":"exitTime",
                  "@accessType":"outputOnly",
                  "@type":"SFTime"
                },
                {
                  "@name":"interface",
                  "@accessType":"inputOutput",
                  "@type":"MFNode"
                },
                {
                  "@name":"children",
                  "@accessType":"inputOutput",
                  "@type":"MFNode"
                }
              ]
            }
          },
          { "ExternProtoDeclare":
            {
              "@name":"Bool",
              "@url":["Bool_proto.x3d"],
              "field": [
                {
                  "@name":"value",
                  "@accessType":"inputOutput",
                  "@type":"SFBool"
                },
                {
                  "@name":"startTime",
                  "@accessType":"inputOutput",
                  "@type":"SFTime"
                },
                {
                  "@name":"bool",
                  "@accessType":"outputOnly",
                  "@type":"SFBool"
                }
              ]
            }
          },
          { "ExternProtoDeclare":
            {
              "@name":"Int",
              "@url":["Int_proto.x3d"],
              "field": [
                {
                  "@name":"value",
                  "@accessType":"inputOutput",
                  "@type":"SFInt32"
                },
                {
                  "@name":"startTime",
                  "@accessType":"inputOutput",
                  "@type":"SFTime"
                },
                {
                  "@name":"int",
                  "@accessType":"outputOnly",
                  "@type":"SFInt32"
                }
              ]
            }
          },
          { "ExternProtoDeclare":
            {
              "@name":"Import",
              "@url":["Import_proto.x3d"],
              "field": [
                {
                  "@name":"url",
                  "@accessType":"inputOutput",
                  "@type":"MFString"
                },
                {
                  "@name":"startTime",
                  "@accessType":"inputOutput",
                  "@type":"SFTime"
                },
                {
                  "@name":"isActive",
                  "@accessType":"outputOnly",
                  "@type":"SFBool"
                },
                {
                  "@name":"exitTime",
                  "@accessType":"outputOnly",
                  "@type":"SFTime"
                },
                {
                  "@name":"parameter",
                  "@accessType":"inputOutput",
                  "@type":"MFNode"
                },
                {
                  "@name":"children",
                  "@accessType":"inputOutput",
                  "@type":"MFNode"
                }
              ]
            }
          },
          { "WorldInfo":
            {
              "@info":[", ","Created in CosmoWorldsPackaged by CosmoPackage"]
            }
          },
          { "Viewpoint":
            {
              "@DEF":"VP2",
              "@description":"viewpoint1",
              "@position":[0.0690002,1.5,43.753]
            }
          },
          { "NavigationInfo":
            {
              "@DEF":"_NoNameNavInfo2",
              "@type":"\"NONE\"",
              "@headlight":false
            }
          },
          { "Transform":
            {
              "@DEF":"HUDWorld",
              "-children":[
                { "ProtoInstance":
                  {
                    "@name":"World",
                    "fieldValue": [
                      {
                        "@name":"interface",
                        "-children":[
                          { "ProtoInstance":
                            {
                              "@name":"Bool",
                              "@DEF":"_1"
                            }
                          },
                          { "ProtoInstance":
                            {
                              "@name":"Bool",
                              "@DEF":"_2"
                            }
                          },
                          { "ProtoInstance":
                            {
                              "@name":"Bool",
                              "@DEF":"_3"
                            }
                          },
                          { "ProtoInstance":
                            {
                              "@name":"Bool",
                              "@DEF":"_4"
                            }
                          },
                          { "ProtoInstance":
                            {
                              "@name":"Bool",
                              "@DEF":"_5"
                            }
                          },
                          { "ProtoInstance":
                            {
                              "@name":"Bool",
                              "@DEF":"_6"
                            }
                          },
                          { "ProtoInstance":
                            {
                              "@name":"Bool",
                              "@DEF":"_7"
                            }
                          },
                          { "ProtoInstance":
                            {
                              "@name":"Int",
                              "@DEF":"_8"
                            }
                          }
                        ]
                      },
                      {
                        "@name":"children",
                        "-children":[
                          { "ProtoInstance":
                            {
                              "@name":"Import",
                              "@DEF":"_9",
                              "fieldValue": [
                                {
                                  "@name":"url",
                                  "@value":[", ","hud.x3dfile:/net/usr/customer/mbm/projects/veag-presentation/vrml/medienfassade/hud/hud.x3d"]
                                }
                              ]
                            }
                          }
                        ]
                      }
                    ]
                  }
                }
              ]
            }
          },
          { "Transform":
            {
              "@DEF":"SceneWorld",
              "-children":[
                { "ProtoInstance":
                  {
                    "@name":"World",
                    "fieldValue": [
                      {
                        "@name":"interface",
                        "-children":[
                          { "ProtoInstance":
                            {
                              "@name":"Bool",
                              "@DEF":"_10"
                            }
                          },
                          { "ProtoInstance":
                            {
                              "@name":"Bool",
                              "@DEF":"_11"
                            }
                          },
                          { "ProtoInstance":
                            {
                              "@name":"Bool",
                              "@DEF":"_12"
                            }
                          },
                          { "ProtoInstance":
                            {
                              "@name":"Bool",
                              "@DEF":"_13"
                            }
                          },
                          { "ProtoInstance":
                            {
                              "@name":"Bool",
                              "@DEF":"_14"
                            }
                          },
                          { "ProtoInstance":
                            {
                              "@name":"Bool",
                              "@DEF":"_15"
                            }
                          },
                          { "ProtoInstance":
                            {
                              "@name":"Bool",
                              "@DEF":"_16"
                            }
                          },
                          { "ProtoInstance":
                            {
                              "@name":"Int",
                              "@DEF":"_17"
                            }
                          }
                        ]
                      },
                      {
                        "@name":"children",
                        "-children":[
                          { "ProtoInstance":
                            {
                              "@name":"Import",
                              "@DEF":"_18",
                              "fieldValue": [
                                {
                                  "@name":"url",
                                  "@value":[", ","scene.x3dfile:/net/usr/customer/mbm/projects/veag-presentation/vrml/medienfassade/scene.x3d"]
                                },
                                {
                                  "@name":"startTime",
                                  "@value":1
                                }
                              ]
                            }
                          }
                        ]
                      }
                    ]
                  }
                }
              ]
            }
          },
          { "ROUTE":
            {
              "@fromNode":"_18",
              "@fromField":"exitTime",
              "@toNode":"_9",
              "@toField":"set_startTime"
            }
          },
          { "ROUTE":
            {
              "@fromNode":"_1",
              "@fromField":"value_changed",
              "@toNode":"_10",
              "@toField":"set_value"
            }
          },
          { "ROUTE":
            {
              "@fromNode":"_2",
              "@fromField":"value_changed",
              "@toNode":"_11",
              "@toField":"set_value"
            }
          },
          { "ROUTE":
            {
              "@fromNode":"_3",
              "@fromField":"value_changed",
              "@toNode":"_12",
              "@toField":"set_value"
            }
          },
          { "ROUTE":
            {
              "@fromNode":"_4",
              "@fromField":"value_changed",
              "@toNode":"_13",
              "@toField":"set_value"
            }
          },
          { "ROUTE":
            {
              "@fromNode":"_5",
              "@fromField":"value_changed",
              "@toNode":"_14",
              "@toField":"set_value"
            }
          },
          { "ROUTE":
            {
              "@fromNode":"_6",
              "@fromField":"value_changed",
              "@toNode":"_15",
              "@toField":"set_value"
            }
          },
          { "ROUTE":
            {
              "@fromNode":"_7",
              "@fromField":"value_changed",
              "@toNode":"_16",
              "@toField":"set_value"
            }
          },
          { "ROUTE":
            {
              "@fromNode":"_8",
              "@fromField":"value_changed",
              "@toNode":"_17",
              "@toField":"set_value"
            }
          }
        ]
    }
  }
}