{ "X3D": {
    "encoding":"UTF-8",
    "@profile":"Full",
    "@version":"4.0",
    "@xsd:noNamespaceSchemaLocation":"https://www.web3d.org/specifications/x3d-4.0.xsd",
    "JSON schema":"https://www.web3d.org/specifications/x3d-4.0-JSONSchema.autogenerated.json",
    "head": {
        "component": [
          {
            "@name":"Scripting",
            "@level":1
          },
          {
            "@name":"EnvironmentalEffects",
            "@level":3
          },
          {
            "@name":"Shaders",
            "@level":1
          },
          {
            "@name":"CubeMapTexturing",
            "@level":1
          },
          {
            "@name":"Texturing",
            "@level":1
          },
          {
            "@name":"Rendering",
            "@level":1
          },
          {
            "@name":"Grouping",
            "@level":3
          },
          {
            "@name":"Core",
            "@level":1
          },
          {
            "@name":"DIS",
            "@level":2
          }
        ],
        "-children":[
          {
            "#comment":"<component name='Shape' level='4'></component>"
          },
          {
            "#comment":"Additional authoring resources for meta-tags: http://www.dublincore.org/documents/dcmi-terms http://www.dublincore.org/documents/dces http://www.w3.org/TR/html4/struct/global.html#h-7.4.4 http://vancouver-webpages.com/META http://vancouver-webpages.com/META/about-mk-metas2.html Additional authoring resources for language codes: ftp://ftp.isi.edu/in-notes/bcp/bcp47.txt http://www.loc.gov/standards/iso639-2/langhome.html http://www.iana.org/numbers.html#L"
          }
        ],
        "meta": [
          {
            "@name":"title",
            "@content":"bumpyx_itesliders.x3d"
          },
          {
            "@name":"description",
            "@content":"*enter description here, short-sentence summaries preferred*"
          },
          {
            "@name":"creator",
            "@content":"Doug Sanden, Christoph Valentin, John Carlson"
          },
          {
            "@name":"translator",
            "@content":"*if manually translating VRML-to-X3D, enter name of person translating here*"
          },
          {
            "@name":"created",
            "@content":"*enter date of initial version here*"
          },
          {
            "@name":"translated",
            "@content":"*enter date of translation here*"
          },
          {
            "@name":"modified",
            "@content":"*enter date of latest revision here*"
          },
          {
            "@name":"version",
            "@content":"*enter version here, if any*"
          },
          {
            "@name":"reference",
            "@content":"*enter reference citation or relative/online url here*"
          },
          {
            "@name":"reference",
            "@content":"*enter additional url/bibliographic reference information here*"
          },
          {
            "@name":"requires",
            "@content":"*enter reference resource here if required to support function, delivery, or coherence of content*"
          },
          {
            "@name":"rights",
            "@content":"*enter copyright information here* Example: Copyright (c) Web3D Consortium Inc. 2008, 2024"
          },
          {
            "@name":"drawing",
            "@content":"*enter drawing filename/url here*"
          },
          {
            "@name":"MovingImage",
            "@content":"*enter movie filename/url here*"
          },
          {
            "@name":"photo",
            "@content":"*enter photo filename/url here*"
          },
          {
            "@name":"subject",
            "@content":"*enter subject keywords here*"
          },
          {
            "@name":"accessRights",
            "@content":"*enter permission statements or url here*"
          },
          {
            "@name":"identifier",
            "@content":"*enter online Uniform Resource Identifier (URI) or Uniform Resource Locator (URL) address for this file here*"
          },
          {
            "@name":"generator",
            "@content":"PSPad, http://www.pspad.com/"
          },
          {
            "@name":"license",
            "@content":"license.html"
          },
          {
            "@name":"translated",
            "@content":"26 April 2025"
          },
          {
            "@name":"generator",
            "@content":"X3dToJson.xslt, https://www.web3d.org/x3d/stylesheets/X3dToJson.html"
          },
          {
            "@name":"reference",
            "@content":"X3D JSON encoding: https://www.web3d.org/wiki/index.php/X3D_JSON_Encoding"
          }
        ]
    },
    "-children":[
      {
        "#comment":"\"The Flower Review (TPREV)\", a simple MU scene using DIS Sensor Event Distribution, It is assumed the reviewers (users) have a non-X3D voice channel (e.g. TeamSpeak) open for their \"discussion about the teapot\""
      }
    ],
    "Scene": {
        "-children":[
          {
            "#comment":"LayerSet with two layers, navigation happens in layer 1"
          },
          { "LayerSet":
            {
              "@activeLayer":1,
              "@order":[1,2],
              "-children":[
                {
                  "#comment":"the first Layer contains the main scenery - \"The Review of the Flower (DIS Multiuser)\""
                },
                {
                  "#comment":"the second layer contains the sliders that are moved with the user's display like a HUD (heads up display)"
                }
              ],
              "-layers":[
                { "Layer":
                  {
                    "@pickable":true,
                    "@objectType":["ALL"],
                    "-children":[
                      {
                        "#comment":"basic nodes, which might be present in any scene"
                      },
                      { "NavigationInfo":
                        {
                          "@type":["EXAMINE"],
                          "@avatarSize":[0.25,1.75,0.75]
                        }
                      },
                      { "DirectionalLight":
                        {
                          "@ambientIntensity":0.2,
                          "@direction":[0,-1,-0]
                        }
                      },
                      { "DirectionalLight":
                        {
                          "@ambientIntensity":0.2,
                          "@direction":[-1,-0.1,-1]
                        }
                      },
                      { "Viewpoint":
                        {
                          "@description":"My Overview",
                          "@fieldOfView":1.570796,
                          "@position":[0,1.75,60]
                        }
                      },
                      {
                        "#comment":"this group contains the red/green/blue 3D crosshair"
                      },
                      { "Group":
                        {
                          "-children":[
                            {
                              "#comment":"Arrow X"
                            },
                            { "Transform":
                              {
                                "@translation":[25,0,0],
                                "@rotation":[0,0,-1,1.57],
                                "-children":[
                                  { "Shape":
                                    {
                                      "-geometry":
                                        { "Cylinder":
                                          {
                                            "@DEF":"Shaft",
                                            "@radius":0.35,
                                            "@height":50.0
                                          }
                                        },
                                      "-appearance":
                                        { "Appearance":
                                          {
                                            "-material":
                                              { "Material":
                                                {
                                                  "@DEF":"RED",
                                                  "@diffuseColor":[1,0,0],
                                                  "@emissiveColor":[1,0,0]
                                                }
                                              }
                                          }
                                        }
                                    }
                                  }
                                ]
                              }
                            },
                            { "Transform":
                              {
                                "@translation":[50,0,0],
                                "@rotation":[0,0,-1,1.57],
                                "-children":[
                                  { "Shape":
                                    {
                                      "-geometry":
                                        { "Cone":
                                          {
                                            "@DEF":"Tip",
                                            "@bottomRadius":0.8,
                                            "@height":3.0
                                          }
                                        },
                                      "-appearance":
                                        { "Appearance":
                                          {
                                            "-material":
                                              { "Material":
                                                {
                                                  "@USE":"RED"
                                                }
                                              }
                                          }
                                        }
                                    }
                                  }
                                ]
                              }
                            },
                            {
                              "#comment":"Arrow Y"
                            },
                            { "Transform":
                              {
                                "@translation":[0,25,0],
                                "-children":[
                                  { "Shape":
                                    {
                                      "-geometry":
                                        { "Cylinder":
                                          {
                                            "@USE":"Shaft"
                                          }
                                        },
                                      "-appearance":
                                        { "Appearance":
                                          {
                                            "-material":
                                              { "Material":
                                                {
                                                  "@DEF":"GREEN",
                                                  "@diffuseColor":[0,1,0],
                                                  "@emissiveColor":[0,1,0]
                                                }
                                              }
                                          }
                                        }
                                    }
                                  }
                                ]
                              }
                            },
                            { "Transform":
                              {
                                "@translation":[0,50,0],
                                "-children":[
                                  { "Shape":
                                    {
                                      "-geometry":
                                        { "Cone":
                                          {
                                            "@USE":"Tip"
                                          }
                                        },
                                      "-appearance":
                                        { "Appearance":
                                          {
                                            "-material":
                                              { "Material":
                                                {
                                                  "@USE":"GREEN"
                                                }
                                              }
                                          }
                                        }
                                    }
                                  }
                                ]
                              }
                            },
                            {
                              "#comment":"Arrow Z"
                            },
                            { "Transform":
                              {
                                "@translation":[0,0,25],
                                "@rotation":[1,0,0,1.57],
                                "-children":[
                                  { "Shape":
                                    {
                                      "-geometry":
                                        { "Cylinder":
                                          {
                                            "@USE":"Shaft"
                                          }
                                        },
                                      "-appearance":
                                        { "Appearance":
                                          {
                                            "-material":
                                              { "Material":
                                                {
                                                  "@DEF":"BLUE",
                                                  "@diffuseColor":[0,0,1],
                                                  "@emissiveColor":[0,0,1]
                                                }
                                              }
                                          }
                                        }
                                    }
                                  }
                                ]
                              }
                            },
                            { "Transform":
                              {
                                "@translation":[0,0,50],
                                "@rotation":[1,0,0,1.57],
                                "-children":[
                                  { "Shape":
                                    {
                                      "-geometry":
                                        { "Cone":
                                          {
                                            "@USE":"Tip"
                                          }
                                        },
                                      "-appearance":
                                        { "Appearance":
                                          {
                                            "-material":
                                              { "Material":
                                                {
                                                  "@USE":"BLUE"
                                                }
                                              }
                                          }
                                        }
                                    }
                                  }
                                ]
                              }
                            }
                          ]
                        }
                      },
                      {
                        "#comment":"the model that is being reviewed by the users of this scene"
                      },
                      { "Transform":
                        {
                          "@DEF":"FlowerTransform",
                          "-children":[
                            {
                              "#comment":"<Inline DEF=\"Flower\" url='\"bumpyx_ite.x3d\"' />"
                            },
                            {
                              "#comment":"Images courtesy of Paul Debevec's Light Probe Image Gallery"
                            },
                            { "Background":
                              {
                                "@backUrl":["../resources/images/all_probes/stpeters_cross/stpeters_back.png","https://coderextreme.net/X3DJSONLD/src/main/resources/images/all_probes/stpeters_cross/stpeters_back.png"],
                                "@bottomUrl":["../resources/images/all_probes/stpeters_cross/stpeters_bottom.png","https://coderextreme.net/X3DJSONLD/src/main/resources/images/all_probes/stpeters_cross/stpeters_bottom.png"],
                                "@frontUrl":["../resources/images/all_probes/stpeters_cross/stpeters_front.png","https://coderextreme.net/X3DJSONLD/src/main/resources/images/all_probes/stpeters_cross/stpeters_front.png"],
                                "@leftUrl":["../resources/images/all_probes/stpeters_cross/stpeters_left.png","https://coderextreme.net/X3DJSONLD/src/main/resources/images/all_probes/stpeters_cross/stpeters_left.png"],
                                "@rightUrl":["../resources/images/all_probes/stpeters_cross/stpeters_right.png","https://coderextreme.net/X3DJSONLD/src/main/resources/images/all_probes/stpeters_cross/stpeters_right.png"],
                                "@topUrl":["../resources/images/all_probes/stpeters_cross/stpeters_top.png","https://coderextreme.net/X3DJSONLD/src/main/resources/images/all_probes/stpeters_cross/stpeters_top.png"]
                              }
                            },
                            { "Transform":
                              {
                                "-children":[
                                  { "Shape":
                                    {
                                      "-geometry":
                                        { "Sphere":
                                          {
                                            "@radius":40
                                          }
                                        },
                                      "-appearance":
                                        { "Appearance":
                                          {
                                            "-material":
                                              { "Material":
                                                {
                                                  "@diffuseColor":[0.7,0.7,0.7],
                                                  "@specularColor":[0.5,0.5,0.5]
                                                }
                                              },
                                            "-texture":
                                              { "ComposedCubeMapTexture":
                                                {
                                                  "@DEF":"texture",
                                                  "-backTexture":
                                                    { "ImageTexture":
                                                      {
                                                        "@url":["../resources/images/all_probes/stpeters_cross/stpeters_back.png","https://coderextreme.net/X3DJSONLD/src/main/resources/images/all_probes/stpeters_cross/stpeters_back.png"]
                                                      }
                                                    },
                                                  "-bottomTexture":
                                                    { "ImageTexture":
                                                      {
                                                        "@url":["../resources/images/all_probes/stpeters_cross/stpeters_bottom.png","https://coderextreme.net/X3DJSONLD/src/main/resources/images/all_probes/stpeters_cross/stpeters_bottom.png"]
                                                      }
                                                    },
                                                  "-frontTexture":
                                                    { "ImageTexture":
                                                      {
                                                        "@url":["../resources/images/all_probes/stpeters_cross/stpeters_front.png","https://coderextreme.net/X3DJSONLD/src/main/resources/images/all_probes/stpeters_cross/stpeters_front.png"]
                                                      }
                                                    },
                                                  "-leftTexture":
                                                    { "ImageTexture":
                                                      {
                                                        "@url":["../resources/images/all_probes/stpeters_cross/stpeters_left.png","https://coderextreme.net/X3DJSONLD/src/main/resources/images/all_probes/stpeters_cross/stpeters_left.png"]
                                                      }
                                                    },
                                                  "-rightTexture":
                                                    { "ImageTexture":
                                                      {
                                                        "@url":["../resources/images/all_probes/stpeters_cross/stpeters_right.png","https://coderextreme.net/X3DJSONLD/src/main/resources/images/all_probes/stpeters_cross/stpeters_right.png"]
                                                      }
                                                    },
                                                  "-topTexture":
                                                    { "ImageTexture":
                                                      {
                                                        "@url":["../resources/images/all_probes/stpeters_cross/stpeters_top.png","https://coderextreme.net/X3DJSONLD/src/main/resources/images/all_probes/stpeters_cross/stpeters_top.png"]
                                                      }
                                                    }
                                                }
                                              },
                                            "-shaders":[
                                              { "ComposedShader":
                                                {
                                                  "@DEF":"x_iteShader",
                                                  "@language":"GLSL",
                                                  "field": [
                                                    {
                                                      "@name":"chromaticDispertion",
                                                      "@accessType":"inputOnly",
                                                      "@type":"SFVec3f",
                                                      "@value":[0.98,1.0,1.033]
                                                    },
                                                    {
                                                      "@name":"cube",
                                                      "@type":"SFNode",
                                                      "@accessType":"inputOnly",
                                                      "-children":[
                                                        { "ComposedCubeMapTexture":
                                                          {
                                                            "@USE":"texture"
                                                          }
                                                        }
                                                      ]
                                                    },
                                                    {
                                                      "@name":"bias",
                                                      "@type":"SFFloat",
                                                      "@accessType":"inputOnly",
                                                      "@value":0.5
                                                    },
                                                    {
                                                      "@name":"scale",
                                                      "@type":"SFFloat",
                                                      "@accessType":"inputOnly",
                                                      "@value":0.5
                                                    },
                                                    {
                                                      "@name":"power",
                                                      "@type":"SFFloat",
                                                      "@accessType":"inputOnly",
                                                      "@value":2
                                                    },
                                                    {
                                                      "@name":"a",
                                                      "@type":"SFFloat",
                                                      "@accessType":"inputOutput",
                                                      "@value":15
                                                    },
                                                    {
                                                      "@name":"b",
                                                      "@type":"SFFloat",
                                                      "@accessType":"inputOutput",
                                                      "@value":5
                                                    },
                                                    {
                                                      "@name":"c",
                                                      "@type":"SFFloat",
                                                      "@accessType":"inputOutput",
                                                      "@value":5
                                                    },
                                                    {
                                                      "@name":"d",
                                                      "@type":"SFFloat",
                                                      "@accessType":"inputOutput",
                                                      "@value":5
                                                    },
                                                    {
                                                      "@name":"tdelta",
                                                      "@type":"SFFloat",
                                                      "@accessType":"inputOutput",
                                                      "@value":0
                                                    },
                                                    {
                                                      "@name":"pdelta",
                                                      "@type":"SFFloat",
                                                      "@accessType":"inputOutput",
                                                      "@value":0
                                                    }
                                                  ],
                                                  "-parts":[
                                                    { "ShaderPart":
                                                      {
                                                        "@url":["../shaders/x_ite_flowers_chromatic.vs","https://coderextreme.net/X3DJSONLD/src/main/shaders/x_ite_flowers_chromatic.vs"],
                                                        "@type":"VERTEX"
                                                      }
                                                    },
                                                    { "ShaderPart":
                                                      {
                                                        "@url":["../shaders/x_ite.fs","https://coderextreme.net/X3DJSONLD/src/main/shaders/x_ite.fs"],
                                                        "@type":"FRAGMENT"
                                                      }
                                                    }
                                                  ],
                                                  "-children":[
                                                    {
                                                      "#comment":"TO CONVERT TO A SPHERE <ShaderPart url='\"../shaders/x_ite.vs\" \"https://coderextreme.net/X3DJSONLD/src/main/shaders/x_ite.vs\"' type=\"VERTEX\" containerField='parts'></ShaderPart> <ShaderPart url='\"../shaders/x_itebubbles.fs\" \"https://coderextreme.net/X3DJSONLD/src/main/shaders/x_itebubbles.fs\"' containerField='parts' type='FRAGMENT'></ShaderPart>"
                                                    }
                                                  ]
                                                }
                                              }
                                            ]
                                          }
                                        }
                                    }
                                  }
                                ]
                              }
                            }
                          ]
                        }
                      },
                      {
                        "#comment":"DIS multiuser facilities"
                      },
                      { "DISEntityManager":
                        {
                          "@DEF":"EntityManager",
                          "@networkMode":"networkReader",
                          "-children":[
                            { "DISEntityTypeMapping":
                              {
                                "@category":77,
                                "@specific":1,
                                "@url":["Leif8Final.x3d"]
                              }
                            },
                            { "DISEntityTypeMapping":
                              {
                                "@category":77,
                                "@specific":2,
                                "@url":["Lily8Final.x3d"]
                              }
                            }
                          ]
                        }
                      },
                      { "Collision":
                        {
                          "@enabled":false,
                          "-children":[
                            { "Group":
                              {
                                "@DEF":"AvatarHolder"
                              }
                            }
                          ]
                        }
                      },
                      { "ROUTE":
                        {
                          "@fromField":"addedEntities",
                          "@fromNode":"EntityManager",
                          "@toField":"addChildren",
                          "@toNode":"AvatarHolder"
                        }
                      },
                      { "ROUTE":
                        {
                          "@fromField":"removedEntities",
                          "@fromNode":"EntityManager",
                          "@toField":"removeChildren",
                          "@toNode":"AvatarHolder"
                        }
                      }
                    ]
                  }
                },
                { "LayoutLayer":
                  {
                    "@pickable":true,
                    "@objectType":["ALL"],
                    "-children":[
                      {
                        "#comment":"positioning the LayoutLayer"
                      },
                      {
                        "#comment":"clipping the LayoutLayer"
                      },
                      {
                        "#comment":"the content (children) of the LayoutLayer"
                      },
                      {
                        "#comment":"first, the slider for scaling the model"
                      },
                      { "Transform":
                        {
                          "@translation":[0,0,-3],
                          "-children":[
                            { "Shape":
                              {
                                "-appearance":
                                  { "Appearance":
                                    {
                                      "-material":
                                        { "Material":
                                          {
                                            "@diffuseColor":[0,0,0],
                                            "@transparency":0.7
                                          }
                                        }
                                    }
                                  },
                                "-geometry":
                                  { "Box":
                                    {
                                      "@size":[100,100,0.02]
                                    }
                                  }
                              }
                            }
                          ]
                        }
                      },
                      {
                        "#comment":"the plane sensors"
                      },
                      { "Transform":
                        {
                          "@DEF":"aSlider",
                          "@translation":[0,0.7,0],
                          "-children":[
                            { "Transform":
                              {
                                "@rotation":[0,0,1,1.57],
                                "-children":[
                                  { "Shape":
                                    {
                                      "-appearance":
                                        { "Appearance":
                                          {
                                            "-material":
                                              { "Material":
                                                {
                                                }
                                              }
                                          }
                                        },
                                      "-geometry":
                                        { "Cylinder":
                                          {
                                            "@radius":0.05,
                                            "@height":2.5
                                          }
                                        }
                                    }
                                  }
                                ]
                              }
                            },
                            { "Transform":
                              {
                                "@DEF":"aTransform",
                                "@translation":[0,0,0.1],
                                "-children":[
                                  { "PlaneSensor":
                                    {
                                      "@DEF":"aSensor",
                                      "@minPosition":[-20,0],
                                      "@maxPosition":[20,0]
                                    }
                                  },
                                  { "Transform":
                                    {
                                      "@translation":[0,0.0,0],
                                      "-children":[
                                        { "TouchSensor":
                                          {
                                            "@DEF":"aTS"
                                          }
                                        },
                                        { "Shape":
                                          {
                                            "-geometry":
                                              { "Sphere":
                                                {
                                                  "@radius":0.08
                                                }
                                              },
                                            "-appearance":
                                              { "Appearance":
                                                {
                                                  "-material":
                                                    { "Material":
                                                      {
                                                        "@diffuseColor":[1,0,0]
                                                      }
                                                    }
                                                }
                                              }
                                          }
                                        }
                                      ]
                                    }
                                  },
                                  { "Shape":
                                    {
                                      "-geometry":
                                        { "Cylinder":
                                          {
                                            "@radius":0.05,
                                            "@height":0.3
                                          }
                                        },
                                      "-appearance":
                                        { "Appearance":
                                          {
                                            "-material":
                                              { "Material":
                                                {
                                                }
                                              }
                                          }
                                        }
                                    }
                                  }
                                ]
                              }
                            },
                            { "Transform":
                              {
                                "@rotation":[0,0,1,1.57],
                                "-children":[
                                  { "Shape":
                                    {
                                      "-appearance":
                                        { "Appearance":
                                          {
                                            "-material":
                                              { "Material":
                                                {
                                                }
                                              }
                                          }
                                        },
                                      "-geometry":
                                        { "Cylinder":
                                          {
                                            "@radius":0.05,
                                            "@height":2.5
                                          }
                                        }
                                    }
                                  }
                                ]
                              }
                            }
                          ]
                        }
                      },
                      { "Transform":
                        {
                          "@DEF":"bSlider",
                          "@translation":[0,0.4,0],
                          "-children":[
                            { "Transform":
                              {
                                "@rotation":[0,0,1,1.57],
                                "-children":[
                                  { "Shape":
                                    {
                                      "-appearance":
                                        { "Appearance":
                                          {
                                            "-material":
                                              { "Material":
                                                {
                                                }
                                              }
                                          }
                                        },
                                      "-geometry":
                                        { "Cylinder":
                                          {
                                            "@radius":0.05,
                                            "@height":2.5
                                          }
                                        }
                                    }
                                  }
                                ]
                              }
                            },
                            { "Transform":
                              {
                                "@DEF":"bTransform",
                                "@translation":[0,0,0.1],
                                "-children":[
                                  { "PlaneSensor":
                                    {
                                      "@DEF":"bSensor",
                                      "@minPosition":[-20,0],
                                      "@maxPosition":[20,0]
                                    }
                                  },
                                  { "Transform":
                                    {
                                      "@translation":[0,0.0,0],
                                      "-children":[
                                        { "TouchSensor":
                                          {
                                            "@DEF":"bTS"
                                          }
                                        },
                                        { "Shape":
                                          {
                                            "-geometry":
                                              { "Sphere":
                                                {
                                                  "@radius":0.08
                                                }
                                              },
                                            "-appearance":
                                              { "Appearance":
                                                {
                                                  "-material":
                                                    { "Material":
                                                      {
                                                        "@diffuseColor":[1,0,0]
                                                      }
                                                    }
                                                }
                                              }
                                          }
                                        }
                                      ]
                                    }
                                  },
                                  { "Shape":
                                    {
                                      "-geometry":
                                        { "Cylinder":
                                          {
                                            "@radius":0.05,
                                            "@height":0.3
                                          }
                                        },
                                      "-appearance":
                                        { "Appearance":
                                          {
                                            "-material":
                                              { "Material":
                                                {
                                                }
                                              }
                                          }
                                        }
                                    }
                                  }
                                ]
                              }
                            }
                          ]
                        }
                      },
                      { "Transform":
                        {
                          "@DEF":"cSlider",
                          "@translation":[0,0.1,0],
                          "-children":[
                            { "Transform":
                              {
                                "@rotation":[0,0,1,1.57],
                                "-children":[
                                  { "Shape":
                                    {
                                      "-appearance":
                                        { "Appearance":
                                          {
                                            "-material":
                                              { "Material":
                                                {
                                                }
                                              }
                                          }
                                        },
                                      "-geometry":
                                        { "Cylinder":
                                          {
                                            "@radius":0.05,
                                            "@height":2.5
                                          }
                                        }
                                    }
                                  }
                                ]
                              }
                            },
                            { "Transform":
                              {
                                "@DEF":"cTransform",
                                "@translation":[0,0,0.1],
                                "-children":[
                                  { "PlaneSensor":
                                    {
                                      "@DEF":"cSensor",
                                      "@minPosition":[-20,0],
                                      "@maxPosition":[20,0]
                                    }
                                  },
                                  { "Transform":
                                    {
                                      "@translation":[0,0.0,0],
                                      "-children":[
                                        { "TouchSensor":
                                          {
                                            "@DEF":"cTS"
                                          }
                                        },
                                        { "Shape":
                                          {
                                            "-geometry":
                                              { "Sphere":
                                                {
                                                  "@radius":0.08
                                                }
                                              },
                                            "-appearance":
                                              { "Appearance":
                                                {
                                                  "-material":
                                                    { "Material":
                                                      {
                                                        "@diffuseColor":[1,0,0]
                                                      }
                                                    }
                                                }
                                              }
                                          }
                                        }
                                      ]
                                    }
                                  },
                                  { "Shape":
                                    {
                                      "-geometry":
                                        { "Cylinder":
                                          {
                                            "@radius":0.05,
                                            "@height":0.3
                                          }
                                        },
                                      "-appearance":
                                        { "Appearance":
                                          {
                                            "-material":
                                              { "Material":
                                                {
                                                }
                                              }
                                          }
                                        }
                                    }
                                  }
                                ]
                              }
                            }
                          ]
                        }
                      },
                      { "Transform":
                        {
                          "@DEF":"dSlider",
                          "@translation":[0,-0.2,0],
                          "-children":[
                            { "Transform":
                              {
                                "@rotation":[0,0,1,1.57],
                                "-children":[
                                  { "Shape":
                                    {
                                      "-appearance":
                                        { "Appearance":
                                          {
                                            "-material":
                                              { "Material":
                                                {
                                                }
                                              }
                                          }
                                        },
                                      "-geometry":
                                        { "Cylinder":
                                          {
                                            "@radius":0.05,
                                            "@height":2.5
                                          }
                                        }
                                    }
                                  }
                                ]
                              }
                            },
                            { "Transform":
                              {
                                "@DEF":"dTransform",
                                "@translation":[0,0,0.1],
                                "-children":[
                                  { "PlaneSensor":
                                    {
                                      "@DEF":"dSensor",
                                      "@minPosition":[-20,0],
                                      "@maxPosition":[20,0]
                                    }
                                  },
                                  { "Transform":
                                    {
                                      "@translation":[0,0.0,0],
                                      "-children":[
                                        { "TouchSensor":
                                          {
                                            "@DEF":"dTS"
                                          }
                                        },
                                        { "Shape":
                                          {
                                            "-geometry":
                                              { "Sphere":
                                                {
                                                  "@radius":0.08
                                                }
                                              },
                                            "-appearance":
                                              { "Appearance":
                                                {
                                                  "-material":
                                                    { "Material":
                                                      {
                                                        "@diffuseColor":[1,0,0]
                                                      }
                                                    }
                                                }
                                              }
                                          }
                                        }
                                      ]
                                    }
                                  },
                                  { "Shape":
                                    {
                                      "-geometry":
                                        { "Cylinder":
                                          {
                                            "@radius":0.05,
                                            "@height":0.3
                                          }
                                        },
                                      "-appearance":
                                        { "Appearance":
                                          {
                                            "-material":
                                              { "Material":
                                                {
                                                }
                                              }
                                          }
                                        }
                                    }
                                  }
                                ]
                              }
                            }
                          ]
                        }
                      },
                      { "Transform":
                        {
                          "@DEF":"pdeltaSlider",
                          "@translation":[0,-0.5,0],
                          "-children":[
                            { "Transform":
                              {
                                "@rotation":[0,0,1,1.57],
                                "-children":[
                                  { "Shape":
                                    {
                                      "-appearance":
                                        { "Appearance":
                                          {
                                            "-material":
                                              { "Material":
                                                {
                                                }
                                              }
                                          }
                                        },
                                      "-geometry":
                                        { "Cylinder":
                                          {
                                            "@radius":0.05,
                                            "@height":2.5
                                          }
                                        }
                                    }
                                  }
                                ]
                              }
                            },
                            { "Transform":
                              {
                                "@DEF":"pdeltaTransform",
                                "@translation":[0,0,0.1],
                                "-children":[
                                  { "PlaneSensor":
                                    {
                                      "@DEF":"pdeltaSensor",
                                      "@minPosition":[-20,0],
                                      "@maxPosition":[20,0]
                                    }
                                  },
                                  { "Transform":
                                    {
                                      "@translation":[0,0.0,0],
                                      "-children":[
                                        { "TouchSensor":
                                          {
                                            "@DEF":"pdeltaTS"
                                          }
                                        },
                                        { "Shape":
                                          {
                                            "-geometry":
                                              { "Sphere":
                                                {
                                                  "@radius":0.08
                                                }
                                              },
                                            "-appearance":
                                              { "Appearance":
                                                {
                                                  "-material":
                                                    { "Material":
                                                      {
                                                        "@diffuseColor":[1,0,0]
                                                      }
                                                    }
                                                }
                                              }
                                          }
                                        }
                                      ]
                                    }
                                  },
                                  { "Shape":
                                    {
                                      "-geometry":
                                        { "Cylinder":
                                          {
                                            "@radius":0.05,
                                            "@height":0.3
                                          }
                                        },
                                      "-appearance":
                                        { "Appearance":
                                          {
                                            "-material":
                                              { "Material":
                                                {
                                                }
                                              }
                                          }
                                        }
                                    }
                                  }
                                ]
                              }
                            }
                          ]
                        }
                      },
                      { "Transform":
                        {
                          "@DEF":"tdeltaSlider",
                          "@translation":[0,-0.8,0],
                          "-children":[
                            { "Transform":
                              {
                                "@rotation":[0,0,1,1.57],
                                "-children":[
                                  { "Shape":
                                    {
                                      "-appearance":
                                        { "Appearance":
                                          {
                                            "-material":
                                              { "Material":
                                                {
                                                }
                                              }
                                          }
                                        },
                                      "-geometry":
                                        { "Cylinder":
                                          {
                                            "@radius":0.05,
                                            "@height":2.5
                                          }
                                        }
                                    }
                                  }
                                ]
                              }
                            },
                            { "Transform":
                              {
                                "@DEF":"tdeltaTransform",
                                "@translation":[0,0,0.1],
                                "-children":[
                                  { "PlaneSensor":
                                    {
                                      "@DEF":"tdeltaSensor",
                                      "@minPosition":[-20,0],
                                      "@maxPosition":[20,0]
                                    }
                                  },
                                  { "Transform":
                                    {
                                      "@translation":[0,0.0,0],
                                      "-children":[
                                        { "TouchSensor":
                                          {
                                            "@DEF":"tdeltaTS"
                                          }
                                        },
                                        { "Shape":
                                          {
                                            "-geometry":
                                              { "Sphere":
                                                {
                                                  "@radius":0.08
                                                }
                                              },
                                            "-appearance":
                                              { "Appearance":
                                                {
                                                  "-material":
                                                    { "Material":
                                                      {
                                                        "@diffuseColor":[1,0,0]
                                                      }
                                                    }
                                                }
                                              }
                                          }
                                        }
                                      ]
                                    }
                                  },
                                  { "Shape":
                                    {
                                      "-geometry":
                                        { "Cylinder":
                                          {
                                            "@radius":0.05,
                                            "@height":0.3
                                          }
                                        },
                                      "-appearance":
                                        { "Appearance":
                                          {
                                            "-material":
                                              { "Material":
                                                {
                                                }
                                              }
                                          }
                                        }
                                    }
                                  }
                                ]
                              }
                            }
                          ]
                        }
                      },
                      { "Script":
                        {
                          "@DEF":"aValueTransformerScript",
                          "@directOutput":true,
                          "@mustEvaluate":true,
                          "field": [
                            {
                              "@name":"newTranslation",
                              "@accessType":"inputOnly",
                              "@type":"SFVec3f",
                              "@value":[1.0,1.0,1.0]
                            },
                            {
                              "@name":"aValue_changed",
                              "@accessType":"outputOnly",
                              "@type":"SFFloat",
                              "@value":1.0
                            }
                          ],
                          "#sourceCode":[
"",
"\t  ecmascript: function newTranslation(Value) { aValue_changed = Value.x * 30; }",
""
]
                        }
                      },
                      { "Script":
                        {
                          "@DEF":"bValueTransformerScript",
                          "@directOutput":true,
                          "@mustEvaluate":true,
                          "field": [
                            {
                              "@name":"newTranslation",
                              "@accessType":"inputOnly",
                              "@type":"SFVec3f",
                              "@value":[1.0,1.0,1.0]
                            },
                            {
                              "@name":"bValue_changed",
                              "@accessType":"outputOnly",
                              "@type":"SFFloat",
                              "@value":1.0
                            }
                          ],
                          "#sourceCode":[
"",
"\t  ecmascript: function newTranslation(Value) { bValue_changed = Value.x * 30; }",
""
]
                        }
                      },
                      { "Script":
                        {
                          "@DEF":"cValueTransformerScript",
                          "@directOutput":true,
                          "@mustEvaluate":true,
                          "field": [
                            {
                              "@name":"newTranslation",
                              "@accessType":"inputOnly",
                              "@type":"SFVec3f",
                              "@value":[1.0,1.0,1.0]
                            },
                            {
                              "@name":"cValue_changed",
                              "@accessType":"outputOnly",
                              "@type":"SFFloat",
                              "@value":1.0
                            }
                          ],
                          "#sourceCode":[
"",
"\t  ecmascript: function newTranslation(Value) { cValue_changed = Value.x * 5; }",
""
]
                        }
                      },
                      { "Script":
                        {
                          "@DEF":"dValueTransformerScript",
                          "@directOutput":true,
                          "@mustEvaluate":true,
                          "field": [
                            {
                              "@name":"newTranslation",
                              "@accessType":"inputOnly",
                              "@type":"SFVec3f",
                              "@value":[1.0,1.0,1.0]
                            },
                            {
                              "@name":"dValue_changed",
                              "@accessType":"outputOnly",
                              "@type":"SFFloat",
                              "@value":1.0
                            }
                          ],
                          "#sourceCode":[
"",
"\t  ecmascript: function newTranslation(Value) { dValue_changed = Value.x * 5; }",
""
]
                        }
                      },
                      { "Script":
                        {
                          "@DEF":"pdeltaValueTransformerScript",
                          "@directOutput":true,
                          "@mustEvaluate":true,
                          "field": [
                            {
                              "@name":"newTranslation",
                              "@accessType":"inputOnly",
                              "@type":"SFVec3f",
                              "@value":[1.0,1.0,1.0]
                            },
                            {
                              "@name":"pdeltaValue_changed",
                              "@accessType":"outputOnly",
                              "@type":"SFFloat",
                              "@value":1.0
                            }
                          ],
                          "#sourceCode":[
"",
"\t  ecmascript: function newTranslation(Value) { pdeltaValue_changed = Value.x; }",
""
]
                        }
                      },
                      { "Script":
                        {
                          "@DEF":"tdeltaValueTransformerScript",
                          "@directOutput":true,
                          "@mustEvaluate":true,
                          "field": [
                            {
                              "@name":"newTranslation",
                              "@accessType":"inputOnly",
                              "@type":"SFVec3f",
                              "@value":[1.0,1.0,1.0]
                            },
                            {
                              "@name":"tdeltaValue_changed",
                              "@accessType":"outputOnly",
                              "@type":"SFFloat",
                              "@value":1.0
                            }
                          ],
                          "#sourceCode":[
"",
"\t  ecmascript: function newTranslation(Value) { tdeltaValue_changed = Value.x; }",
""
]
                        }
                      },
                      { "ROUTE":
                        {
                          "@fromField":"translation_changed",
                          "@fromNode":"aSensor",
                          "@toField":"set_translation",
                          "@toNode":"aTransform"
                        }
                      },
                      { "ROUTE":
                        {
                          "@fromField":"translation_changed",
                          "@fromNode":"bSensor",
                          "@toField":"set_translation",
                          "@toNode":"bTransform"
                        }
                      },
                      { "ROUTE":
                        {
                          "@fromField":"translation_changed",
                          "@fromNode":"cSensor",
                          "@toField":"set_translation",
                          "@toNode":"cTransform"
                        }
                      },
                      { "ROUTE":
                        {
                          "@fromField":"translation_changed",
                          "@fromNode":"dSensor",
                          "@toField":"set_translation",
                          "@toNode":"dTransform"
                        }
                      },
                      { "ROUTE":
                        {
                          "@fromField":"translation_changed",
                          "@fromNode":"pdeltaSensor",
                          "@toField":"set_translation",
                          "@toNode":"pdeltaTransform"
                        }
                      },
                      { "ROUTE":
                        {
                          "@fromField":"translation_changed",
                          "@fromNode":"tdeltaSensor",
                          "@toField":"set_translation",
                          "@toNode":"tdeltaTransform"
                        }
                      },
                      { "ROUTE":
                        {
                          "@fromField":"translation_changed",
                          "@fromNode":"aSensor",
                          "@toField":"newTranslation",
                          "@toNode":"aValueTransformerScript"
                        }
                      },
                      { "ROUTE":
                        {
                          "@fromField":"translation_changed",
                          "@fromNode":"bSensor",
                          "@toField":"newTranslation",
                          "@toNode":"bValueTransformerScript"
                        }
                      },
                      { "ROUTE":
                        {
                          "@fromField":"translation_changed",
                          "@fromNode":"cSensor",
                          "@toField":"newTranslation",
                          "@toNode":"cValueTransformerScript"
                        }
                      },
                      { "ROUTE":
                        {
                          "@fromField":"translation_changed",
                          "@fromNode":"dSensor",
                          "@toField":"newTranslation",
                          "@toNode":"dValueTransformerScript"
                        }
                      },
                      { "ROUTE":
                        {
                          "@fromField":"translation_changed",
                          "@fromNode":"pdeltaSensor",
                          "@toField":"newTranslation",
                          "@toNode":"pdeltaValueTransformerScript"
                        }
                      },
                      { "ROUTE":
                        {
                          "@fromField":"translation_changed",
                          "@fromNode":"tdeltaSensor",
                          "@toField":"newTranslation",
                          "@toNode":"tdeltaValueTransformerScript"
                        }
                      },
                      { "ROUTE":
                        {
                          "@fromField":"aValue_changed",
                          "@fromNode":"aValueTransformerScript",
                          "@toField":"a",
                          "@toNode":"x_iteShader"
                        }
                      },
                      { "ROUTE":
                        {
                          "@fromField":"bValue_changed",
                          "@fromNode":"bValueTransformerScript",
                          "@toField":"b",
                          "@toNode":"x_iteShader"
                        }
                      },
                      { "ROUTE":
                        {
                          "@fromField":"cValue_changed",
                          "@fromNode":"cValueTransformerScript",
                          "@toField":"c",
                          "@toNode":"x_iteShader"
                        }
                      },
                      { "ROUTE":
                        {
                          "@fromField":"dValue_changed",
                          "@fromNode":"dValueTransformerScript",
                          "@toField":"d",
                          "@toNode":"x_iteShader"
                        }
                      },
                      { "ROUTE":
                        {
                          "@fromField":"pdeltaValue_changed",
                          "@fromNode":"pdeltaValueTransformerScript",
                          "@toField":"pdelta",
                          "@toNode":"x_iteShader"
                        }
                      },
                      { "ROUTE":
                        {
                          "@fromField":"tdeltaValue_changed",
                          "@fromNode":"tdeltaValueTransformerScript",
                          "@toField":"tdelta",
                          "@toNode":"x_iteShader"
                        }
                      }
                    ],
                    "-layout":
                      { "Layout":
                        {
                          "@align":["RIGHT","BOTTOM"],
                          "@offset":[0.0,0.2],
                          "@offsetUnits":["WORLD","WORLD"],
                          "@scaleMode":["NONE","NONE"],
                          "@size":[0.4,0.6],
                          "@sizeUnits":["WORLD","WORLD"]
                        }
                      },
                    "-viewport":[
                      { "Viewport":
                        {
                          "@clipBoundary":[0,1,0,1]
                        }
                      }
                    ]
                  }
                }
              ]
            }
          }
        ]
    }
  }
}